fern/VERSION
fern/__init__.py
fern/fern.py
fern_labextension-0.0.13.dist-info/METADATA
fern_labextension-0.0.13.dist-info/WHEEL
fern_labextension-0.0.13.dist-info/top_level.txt
fern_labextension-0.0.13.dist-info/RECORD
