Metadata-Version: 2.1
Name: fern-labextension
Version: 0.0.13
Summary: Fern Jupyter lab Extension
Home-page: https://github.com/disraptoer/fern-next
Author: amie
Author-email: hej@amie.ai
License: private
Platform: UNKNOWN
Requires-Python: >=3.5
Requires-Dist: ipython
Requires-Dist: pandas
Requires-Dist: numpy
Requires-Dist: jupyterlab
Requires-Dist: amieci (>=0.0.7)
